jax2onnx/__init__.py
jax2onnx/converter/__init__.py
jax2onnx/converter/conversion_api.py
jax2onnx/converter/function_scope.py
jax2onnx/converter/ir_builder.py
jax2onnx/converter/ir_constants.py
jax2onnx/converter/ir_context.py
jax2onnx/converter/ir_optimizations.py
jax2onnx/converter/ir_postprocess.py
jax2onnx/converter/lower_dimexpr.py
jax2onnx/converter/typing_support.py
jax2onnx/plugins/__init__.py
jax2onnx/plugins/_axis0_utils.py
jax2onnx/plugins/_complex_utils.py
jax2onnx/plugins/_ir_shapes.py
jax2onnx/plugins/_loop_extent_meta.py
jax2onnx/plugins/_patching.py
jax2onnx/plugins/_post_check_onnx_graph.py
jax2onnx/plugins/_utils.py
jax2onnx/plugins/equinox/__init__.py
jax2onnx/plugins/equinox/eqx/__init__.py
jax2onnx/plugins/equinox/eqx/nn/__init__.py
jax2onnx/plugins/equinox/eqx/nn/conv.py
jax2onnx/plugins/equinox/eqx/nn/dropout.py
jax2onnx/plugins/equinox/eqx/nn/identity.py
jax2onnx/plugins/equinox/eqx/nn/layer_norm.py
jax2onnx/plugins/equinox/eqx/nn/linear.py
jax2onnx/plugins/equinox/eqx/nn/multihead_attention.py
jax2onnx/plugins/equinox/eqx/nn/rms_norm.py
jax2onnx/plugins/equinox/eqx/nn/rotary_positional_embedding.py
jax2onnx/plugins/examples/__init__.py
jax2onnx/plugins/examples/eqx/__init__.py
jax2onnx/plugins/examples/eqx/dino.py
jax2onnx/plugins/examples/eqx/gpt_oss.py
jax2onnx/plugins/examples/eqx/mlp.py
jax2onnx/plugins/examples/eqx/simple_linear.py
jax2onnx/plugins/examples/jaxfluids/__init__.py
jax2onnx/plugins/examples/jaxfluids/reconstructed_patterns.py
jax2onnx/plugins/examples/jnp/__init__.py
jax2onnx/plugins/examples/jnp/fori_loop.py
jax2onnx/plugins/examples/jnp/issue18.py
jax2onnx/plugins/examples/jnp/select.py
jax2onnx/plugins/examples/jnp/sort.py
jax2onnx/plugins/examples/lax/__init__.py
jax2onnx/plugins/examples/lax/cond_scatter_add_mul.py
jax2onnx/plugins/examples/lax/cond_scatter_repro.py
jax2onnx/plugins/examples/lax/remat2.py
jax2onnx/plugins/examples/lax/scatter_window.py
jax2onnx/plugins/examples/lax/two_times_silu.py
jax2onnx-0.11.2.dist-info/LICENSE
jax2onnx-0.11.2.dist-info/METADATA
jax2onnx-0.11.2.dist-info/WHEEL
jax2onnx-0.11.2.dist-info/RECORD
