Metadata-Version: 2.3
Name: jax2onnx
Version: 0.11.2
Summary: export JAX to ONNX
Author: enpasos
Author-email: matthias.unverzagt@enpasos.ai
Requires-Python: >=3.11,<3.13
Classifier: Programming Language :: Python :: 3
Classifier: Programming Language :: Python :: 3.11
Classifier: Programming Language :: Python :: 3.12
Requires-Dist: einops (>=0.8.1)
Requires-Dist: equinox (>=0.13.1)
Requires-Dist: flax (>=0.12.1)
Requires-Dist: huggingface-hub (>=0.26.0)
Requires-Dist: jax (>=0.7.2)
Requires-Dist: ml_dtypes (>=0.5.1)
Requires-Dist: netron (>=8.2.9)
Requires-Dist: onnx (>=1.17.0)
Requires-Dist: onnx-ir (>=0.1.15)
Requires-Dist: onnxruntime (>=1.19.2)
Requires-Dist: optax (>=0.2.4)
Requires-Dist: orbax-checkpoint (>=0.11.6)
Requires-Dist: orbax-export (>=0.0.6)
